{"id":"186247d4-dbcd-93d8-d348-a19c5328d7a6","name":"babel","timestamp":1428071053946,"requests":[{"collectionId":"186247d4-dbcd-93d8-d348-a19c5328d7a6","id":"243401ac-c9de-71d9-78c7-6ed4b852bdb9","name":"CreateJson","description":"This is used to create JSON out of Raml","url":"http://localhost:8060/api/descriptions","method":"POST","headers":"Accept: application/yaml+raml\n","data":"#%RAML 0.8\n---\ntitle: Test API\nbaseUri: http://www.google.com/\nprotocols: [HTTP]\nversion: 1\nmediaType: application/json\ndocumentation: \n  - title: The Description of the API\n    content: |\n      This is a test\n/api/derp:\n  displayName: GetDerp\n  get:\n    description: deeee\n/api/derp/{id}:\n  displayName: GetDerpById\n  uriParameters: \n      id: \n        type: integer\n        required: false\n        description: \n        example: |\n            \n  get:\n    description: \n/api/derp?value={value}&name={name}:\n  displayName: CreateNewDerp\n  uriParameters: \n      value: \n        type: string\n        required: false\n        description: \n        example: |\n            \n      name: \n        type: string\n        required: false\n        description: \n        example: |\n            \n  post:\n    description: \n/api/tests:\n  displayName:\n  get:\n    description: This gets the tests\n    headers:\n      Accept: \n        displayName: Accept\n        example: application/json\n        type: string\n        description: This is the content type we want from the server\n    responses:\n      400:\n        body:\n          application/json: \n            schema: \n            example: |\n                [bad request]\n      200:\n        body:\n          application/hal+json: \n            schema: values\n            example: |\n                ['value1', 'value2']\n      500:\n        body:\n          application/json: \n            schema: \n            example: |\n                [internal server error]\n  post:\n    \n    description: This inserts a test\n    body:\n      application/yaml: \n        formParameters: \n          testCase: \n            description  : The test\n            type  : string\n            required  : false\n            example  :\n    headers:\n      Accept: \n        displayName: Accept\n        example: application/json\n        type: integer\n        minimum: -1\n        maximum: -2\n        description: This is the content type we want from the server\n    responses:\n      400:\n        body:\n          application/json: \n            schema: \n            example: |\n                [bad request]\n      200:\n        description: |\n          This is the standard request back.\n        body:\n          application/json: \n            schema: \n            example: |\n                [should be the location of this test]\n      500:\n        body:\n          application/json: \n            schema: \n            example: |\n                [internal server error]\n/api/tests/{id}: #name: this\n  displayName: \n  uriParameters: \n      id: \n        type: integer\n        required: false\n        description: id of the test\n        example: |\n            \n  put:\n    description: updates the test\n    body:\n      application/x-www-form-urlencoded:: \n        formParameters: \n          testCase: \n            description  : The test\n            type  : string\n            required  : false\n            example  : \n","dataMode":"raw","timestamp":0,"responses":[],"version":2},{"collectionId":"186247d4-dbcd-93d8-d348-a19c5328d7a6","id":"2a043942-b1eb-c4ba-94de-e183e13efaae","name":"Create C#","description":"This creates text based on json to generate c# client","url":"http://localhost:8060/api/clients","method":"POST","headers":"Accept: text/plain\n","data":"{\n\"description\":{\"title\":\"Test API\",\"baseUri\":\"http://www.google.com/\",\"protocols\":[\"HTTP\"],\"version\":\"1\",\"mediaType\":\"application/json\",\"documentation\":[{\"title\":\"The Description of the API\",\"content\":\"This is a test\\n\"}],\"resources\":[{\"displayName\":\"GetDerp\",\"relativeUri\":\"/api/derp\",\"methods\":[{\"description\":\"deeee\",\"protocols\":[\"HTTP\"],\"method\":\"get\"}],\"relativeUriPathSegments\":[\"api\",\"derp\"]},{\"displayName\":\"GetDerpById\",\"uriParameters\":{\"id\":{\"type\":\"integer\",\"required\":false,\"description\":null,\"example\":\"\",\"displayName\":\"id\"}},\"relativeUri\":\"/api/derp/{id}\",\"methods\":[{\"description\":null,\"protocols\":[\"HTTP\"],\"method\":\"get\"}],\"relativeUriPathSegments\":[\"api\",\"derp\",\"{id}\"]},{\"displayName\":\"CreateNewDerp\",\"uriParameters\":{\"value\":{\"type\":\"string\",\"required\":false,\"description\":null,\"example\":\"\",\"displayName\":\"value\"},\"name\":{\"type\":\"string\",\"required\":false,\"description\":null,\"example\":\"\",\"displayName\":\"name\"}},\"relativeUri\":\"/api/derp?value={value}&name={name}\",\"methods\":[{\"description\":null,\"protocols\":[\"HTTP\"],\"method\":\"post\"}],\"relativeUriPathSegments\":[\"api\",\"derp?value={value}&name={name}\"]},{\"displayName\":null,\"relativeUri\":\"/api/tests\",\"methods\":[{\"description\":\"This gets the tests\",\"headers\":{\"Accept\":{\"displayName\":\"Accept\",\"example\":\"application/json\",\"type\":\"string\",\"description\":\"This is the content type we want from the server\"}},\"responses\":{\"200\":{\"body\":{\"application/hal+json\":{\"schema\":\"values\",\"example\":\"['value1', 'value2']\\n\"}}},\"400\":{\"body\":{\"application/json\":{\"schema\":null,\"example\":\"[bad request]\\n\"}}},\"500\":{\"body\":{\"application/json\":{\"schema\":null,\"example\":\"[internal server error]\\n\"}}}},\"protocols\":[\"HTTP\"],\"method\":\"get\"},{\"description\":\"This inserts a test\",\"body\":{\"application/yaml\":{\"formParameters\":{\"testCase\":{\"description\":\"The test\",\"type\":\"string\",\"required\":false,\"example\":null,\"displayName\":\"testCase\"}}}},\"headers\":{\"Accept\":{\"displayName\":\"Accept\",\"example\":\"application/json\",\"type\":\"integer\",\"minimum\":-1,\"maximum\":-2,\"description\":\"This is the content type we want from the server\"}},\"responses\":{\"200\":{\"description\":\"This is the standard request back.\\n\",\"body\":{\"application/json\":{\"schema\":null,\"example\":\"[should be the location of this test]\\n\"}}},\"400\":{\"body\":{\"application/json\":{\"schema\":null,\"example\":\"[bad request]\\n\"}}},\"500\":{\"body\":{\"application/json\":{\"schema\":null,\"example\":\"[internal server error]\\n\"}}}},\"protocols\":[\"HTTP\"],\"method\":\"post\"}],\"relativeUriPathSegments\":[\"api\",\"tests\"]},{\"displayName\":null,\"uriParameters\":{\"id\":{\"type\":\"integer\",\"required\":false,\"description\":\"id of the test\",\"example\":\"\",\"displayName\":\"id\"}},\"relativeUri\":\"/api/tests/{id}\",\"methods\":[{\"description\":\"updates the test\",\"body\":{\"application/x-www-form-urlencoded:\":{\"formParameters\":{\"testCase\":{\"description\":\"The test\",\"type\":\"string\",\"required\":false,\"example\":null,\"displayName\":\"testCase\"}}}},\"protocols\":[\"HTTP\"],\"method\":\"put\"}],\"relativeUriPathSegments\":[\"api\",\"tests\",\"{id}\"]}]},\n\"languageType\":\"C#\"\n}","dataMode":"raw","timestamp":0,"responses":[],"version":2}]}